README.rst
setup.py
closedown/__init__.py
closedown/closedown.py
closedown.egg-info/PKG-INFO
closedown.egg-info/SOURCES.txt
closedown.egg-info/dependency_links.txt
closedown.egg-info/pbr.json
closedown.egg-info/requires.txt
closedown.egg-info/top_level.txt